imserv/__init__.py
imserv/__main__.py
imserv/api.py
imserv/config.py
imserv/db.py
imserv/main.py
imserv/static/index.css
imserv/static/index.js
imserv/templates/index.html
imserv/util.py
imserv/views.py
imserv-0.1.11.4.dist-info/entry_points.txt
imserv-0.1.11.4.dist-info/LICENSE
imserv-0.1.11.4.dist-info/WHEEL
imserv-0.1.11.4.dist-info/METADATA
imserv-0.1.11.4.dist-info/RECORD
