Metadata-Version: 2.1
Name: imserv
Version: 0.1.11.4
Summary: Spin an image server, store images from Clipboard in single place, and prevent duplication.
Home-page: https://github.com/patarapolw/imserv
License: MIT
Author: Pacharapol Withayasakpunt
Author-email: patarapolw@gmail.com
Classifier: License :: OSI Approved :: MIT License
Classifier: Programming Language :: Python :: 2
Classifier: Programming Language :: Python :: 2.7
Classifier: Programming Language :: Python :: 3
Classifier: Programming Language :: Python :: 3.4
Classifier: Programming Language :: Python :: 3.5
Classifier: Programming Language :: Python :: 3.6
Classifier: Programming Language :: Python :: 3.7
Requires-Dist: click (>=7.0,<8.0)
Requires-Dist: flask (>=1.0,<2.0)
Requires-Dist: imagehash (>=4.0,<5.0)
Requires-Dist: nonrepeat (>=0.1.1,<0.2.0)
Requires-Dist: peewee (>=3.7,<4.0)
Requires-Dist: pillow (>=5.2,<6.0)
Requires-Dist: psycopg2-binary (>=2.7,<3.0)
Requires-Dist: python-slugify (>=1.2,<2.0)
Requires-Dist: send2trash
Requires-Dist: tqdm (>=4.26,<5.0)
Requires-Dist: watchdog (>=0.9.0,<0.10.0)
